{
    "objects": [
        {
            "goal_pos": [
                0.703095409911989,
                -0.7578306987555525,
                0.07500000000000001
            ],
            "goal_quat": [
                0.5459480077694701,
                -0.0,
                -0.0,
                -0.8378190573223712
            ],
            "shape": [
                0.03,
                0.3,
                0.05
            ],
            "start_pos": [
                0.415414081383088,
                0.27894543455352117,
                0.15100000000000002
            ],
            "start_quat": [
                0.6965957791639846,
                -0.0,
                -0.0,
                -0.7174638112482894
            ]
        },
        {
            "goal_pos": [
                -0.861999803567997,
                -0.6365050412990657,
                0.07500000000000001
            ],
            "goal_quat": [
                0.6843931454265475,
                -0.0,
                -0.0,
                -0.7291131753665933
            ],
            "shape": [
                0.03,
                0.3,
                0.05
            ],
            "start_pos": [
                -0.39093690619798777,
                0.30632550550146337,
                0.551
            ],
            "start_quat": [
                0.9996313408223331,
                0.0,
                0.0,
                0.027151103950753395
            ]
        },
        {
            "goal_pos": [
                0.18426086543185013,
                -0.8230382692683793,
                0.07500000000000001
            ],
            "goal_quat": [
                0.4262904797131386,
                0.0,
                0.0,
                0.9045863291615357
            ],
            "shape": [
                0.03,
                0.3,
                0.05
            ],
            "start_pos": [
                -0.018977684282025828,
                0.3258596205040585,
                0.15100000000000002
            ],
            "start_quat": [
                0.905994898869355,
                -0.0,
                -0.0,
                -0.4232886051179588
            ]
        }
    ]
}