{
    "a0_": [
        {
            "name": "a0_",
            "type": 0,
            "start_conf": [
                0.0,
                0.5,
                -1.2,
                0.0,
                1.57,
                1.57
            ],
            "goal_conf": [
                -1.8509773420314808,
                -0.06725085186199585,
                -1.6718890395659454,
                -0.1893575123465131,
                0.8734433054538754,
                0.6513245865909866
            ],
            "start_time": 0,
            "success": 1,
            "planning_time": 53,
            "path": [
                {
                    "q": [
                        0.0,
                        0.5,
                        -1.2,
                        0.0,
                        1.57,
                        1.57
                    ],
                    "t": 0.0
                },
                {
                    "q": [
                        0.2886890459290786,
                        0.10246942321017855,
                        -1.2608365511513622,
                        -0.25205480283481246,
                        1.2013758333356304,
                        2.3153264985498776
                    ],
                    "t": 10.0
                },
                {
                    "q": [
                        -1.8509773420314808,
                        -0.06725085186199585,
                        -1.6718890395659454,
                        -0.1893575123465131,
                        0.8734433054538754,
                        0.6513245865909866
                    ],
                    "t": 37.68005595838335
                }
            ]
        },
        {
            "name": "a0_",
            "type": 0,
            "start_conf": [
                -1.8509773420314772,
                -0.06725085186199564,
                -1.671889039565946,
                -0.189357512346513,
                0.8734433054538753,
                0.651324586590986
            ],
            "goal_conf": [
                -0.35852073164044573,
                0.08445917172238585,
                -1.7329721741264938,
                -0.40514022394407906,
                2.1678764138220736,
                2.488805301833822
            ],
            "start_time": 38,
            "success": 1,
            "planning_time": 193,
            "path": [
                {
                    "q": [
                        -1.8509773420314772,
                        -0.06725085186199564,
                        -1.671889039565946,
                        -0.189357512346513,
                        0.8734433054538753,
                        0.651324586590986
                    ],
                    "t": 38.0
                },
                {
                    "q": [
                        0.3076928688826649,
                        -0.1778725677319282,
                        -0.7973223865717594,
                        -1.3224429716615316,
                        0.09932596311453734,
                        2.0595814120431557
                    ],
                    "t": 68.50129288783319
                },
                {
                    "q": [
                        -0.35852073164044573,
                        0.08445917172238585,
                        -1.7329721741264938,
                        -0.40514022394407906,
                        2.1678764138220736,
                        2.488805301833822
                    ],
                    "t": 94.4020343631413
                }
            ]
        },
        {
            "name": "a0_",
            "type": 0,
            "start_conf": [
                -0.3585207316404464,
                0.08445917172238637,
                -1.7329721741264947,
                -0.40514022394407867,
                2.167876413822073,
                2.488805301833821
            ],
            "goal_conf": [
                0.0,
                0.5,
                -1.2,
                0.0,
                1.57,
                1.57
            ],
            "start_time": 95,
            "success": 1,
            "planning_time": 160,
            "path": [
                {
                    "q": [
                        -0.3585207316404464,
                        0.08445917172238637,
                        -1.7329721741264947,
                        -0.40514022394407867,
                        2.167876413822073,
                        2.488805301833821
                    ],
                    "t": 95.0
                },
                {
                    "q": [
                        -0.06306099506676438,
                        -0.15885327241479755,
                        -1.107063323808173,
                        -0.534561136452103,
                        1.6481957067580075,
                        2.90704315257904
                    ],
                    "t": 105.0
                },
                {
                    "q": [
                        0.0,
                        0.5,
                        -1.2,
                        0.0,
                        1.57,
                        1.57
                    ],
                    "t": 120.90421058276901
                }
            ]
        },
        {
            "name": "a0_",
            "type": 0,
            "start_conf": [
                -0.3585207316404464,
                0.08445917172238637,
                -1.7329721741264947,
                -0.40514022394407867,
                2.167876413822073,
                2.488805301833821
            ],
            "goal_conf": [
                0.3585024858059283,
                0.2912218214311921,
                -1.8389660547294169,
                -0.41624264505472586,
                1.5108849348982358,
                0.5239937135431858
            ],
            "start_time": 95,
            "success": 1,
            "planning_time": 95,
            "path": [
                {
                    "q": [
                        -0.3585207316404464,
                        0.08445917172238637,
                        -1.7329721741264947,
                        -0.40514022394407867,
                        2.167876413822073,
                        2.488805301833821
                    ],
                    "t": 95.0
                },
                {
                    "q": [
                        0.2560115436200229,
                        0.1564481555777832,
                        -1.478006081736975,
                        -0.31658167811810833,
                        1.4817990827613372,
                        2.217484015599136
                    ],
                    "t": 105.0
                },
                {
                    "q": [
                        0.3585024858059283,
                        0.2912218214311921,
                        -1.8389660547294169,
                        -0.41624264505472586,
                        1.5108849348982358,
                        0.5239937135431858
                    ],
                    "t": 122.43886004270938
                }
            ]
        },
        {
            "name": "a0_",
            "type": 0,
            "start_conf": [
                0.3585024858059285,
                0.29122182143119346,
                -1.8389660547294167,
                -0.41624264505472475,
                1.510884934898236,
                0.5239937135431862
            ],
            "goal_conf": [
                1.6406385800350003,
                -0.6619459411512735,
                -0.8921307944855033,
                0.1541397995302674,
                1.945799639747901,
                2.6159242210881266
            ],
            "start_time": 123,
            "success": 1,
            "planning_time": 136,
            "path": [
                {
                    "q": [
                        0.3585024858059285,
                        0.29122182143119346,
                        -1.8389660547294167,
                        -0.41624264505472475,
                        1.510884934898236,
                        0.5239937135431862
                    ],
                    "t": 123.0
                },
                {
                    "q": [
                        2.5040430340309143,
                        -0.7511542304579039,
                        -0.6360987306312806,
                        -0.16837045985021665,
                        1.6752678112431094,
                        2.677745532767322
                    ],
                    "t": 157.4439996604013
                },
                {
                    "q": [
                        1.6406385800350003,
                        -0.6619459411512735,
                        -0.8921307944855033,
                        0.1541397995302674,
                        1.945799639747901,
                        2.6159242210881266
                    ],
                    "t": 167.4784781385398
                }
            ]
        },
        {
            "name": "a0_",
            "type": 0,
            "start_conf": [
                1.6406385800350005,
                -0.6619459411512736,
                -0.892130794485503,
                0.15413979953026669,
                1.9457996397479,
                2.615924221088127
            ],
            "goal_conf": [
                0.0,
                0.5,
                -1.2,
                0.0,
                1.57,
                1.57
            ],
            "start_time": 168,
            "success": 1,
            "planning_time": 92,
            "path": [
                {
                    "q": [
                        1.6406385800350005,
                        -0.6619459411512736,
                        -0.892130794485503,
                        0.15413979953026669,
                        1.9457996397479,
                        2.615924221088127
                    ],
                    "t": 168.0
                },
                {
                    "q": [
                        1.1975483327548773,
                        -0.4913598886910607,
                        -0.9161237899835151,
                        -0.2848188344066124,
                        1.3587164297271492,
                        2.129463133392191
                    ],
                    "t": 178.0
                },
                {
                    "q": [
                        0.0,
                        0.5,
                        -1.2,
                        0.0,
                        1.57,
                        1.57
                    ],
                    "t": 195.14553933923662
                }
            ]
        },
        {
            "name": "a0_",
            "type": 0,
            "start_conf": [
                1.6406385800350005,
                -0.6619459411512736,
                -0.892130794485503,
                0.15413979953026669,
                1.9457996397479,
                2.615924221088127
            ],
            "goal_conf": [
                -0.6763720898347628,
                -0.4423328573795827,
                -1.563880817638503,
                0.021084406576249867,
                0.9685043959414972,
                0.8562830161597561
            ],
            "start_time": 168,
            "success": 1,
            "planning_time": 143,
            "path": [
                {
                    "q": [
                        1.6406385800350005,
                        -0.6619459411512736,
                        -0.892130794485503,
                        0.15413979953026669,
                        1.9457996397479,
                        2.615924221088127
                    ],
                    "t": 168.0
                },
                {
                    "q": [
                        1.9636784258499171,
                        -0.6339181272147235,
                        -0.5781247857790619,
                        0.4182086425619436,
                        1.4406560044373247,
                        1.9293694308468883
                    ],
                    "t": 178.0
                },
                {
                    "q": [
                        -0.6763720898347628,
                        -0.4423328573795827,
                        -1.563880817638503,
                        0.021084406576249867,
                        0.9685043959414972,
                        0.8562830161597561
                    ],
                    "t": 208.8490045606281
                }
            ]
        },
        {
            "name": "a0_",
            "type": 0,
            "start_conf": [
                -0.6763720898347625,
                -0.44233285737958283,
                -1.5638808176385037,
                0.021084406576250103,
                0.9685043959414976,
                0.8562830161597557
            ],
            "goal_conf": [
                -0.4072785356667482,
                0.010680630197211133,
                -1.9885789273807832,
                -0.13102857408870017,
                2.0142113275976485,
                2.2837692698978205
            ],
            "start_time": 209,
            "success": 1,
            "planning_time": 112,
            "path": [
                {
                    "q": [
                        -0.6763720898347625,
                        -0.44233285737958283,
                        -1.5638808176385037,
                        0.021084406576250103,
                        0.9685043959414976,
                        0.8562830161597557
                    ],
                    "t": 209.0
                },
                {
                    "q": [
                        -1.0924363053660116,
                        -0.26368938611912246,
                        -1.0538605553370926,
                        -0.3160465583793398,
                        0.3927082327235343,
                        0.556853722896781
                    ],
                    "t": 219.0
                },
                {
                    "q": [
                        -0.4072785356667482,
                        0.010680630197211133,
                        -1.9885789273807832,
                        -0.13102857408870017,
                        2.0142113275976485,
                        2.2837692698978205
                    ],
                    "t": 245.58849709626062
                }
            ]
        },
        {
            "name": "a0_",
            "type": 0,
            "start_conf": [
                -0.4072785356667482,
                0.010680630197211133,
                -1.9885789273807832,
                -0.13102857408870017,
                2.0142113275976485,
                2.2837692698978205
            ],
            "goal_conf": [
                0.0,
                0.5,
                -1.2,
                0.0,
                1.57,
                1.57
            ],
            "start_time": 246,
            "success": 1,
            "planning_time": 108,
            "path": [
                {
                    "q": [
                        -0.4072785356667482,
                        0.010680630197211133,
                        -1.9885789273807832,
                        -0.13102857408870017,
                        2.0142113275976485,
                        2.2837692698978205
                    ],
                    "t": 246.0
                },
                {
                    "q": [
                        -1.0023275726387881,
                        -0.24019541393485658,
                        -2.151260092233438,
                        -0.34347059511232375,
                        1.6852016682205853,
                        2.918697395295856
                    ],
                    "t": 256.0
                },
                {
                    "q": [
                        0.0,
                        0.5,
                        -1.2,
                        0.0,
                        1.57,
                        1.57
                    ],
                    "t": 277.0044705053492
                }
            ]
        }
    ],
    "a1_": [
        {
            "name": "a1_",
            "type": 0,
            "start_conf": [
                0.0,
                0.5,
                -1.2,
                0.0,
                1.57,
                1.57
            ],
            "goal_conf": [
                1.4381994965024492,
                -0.5174988667368066,
                -1.3573402424316683,
                0.2441849474550369,
                1.3585513994894454,
                0.9164381701896847
            ],
            "start_time": 177,
            "success": 1,
            "planning_time": 187,
            "path": [
                {
                    "q": [
                        0.0,
                        0.5,
                        -1.2,
                        0.0,
                        1.57,
                        1.57
                    ],
                    "t": 177.0
                },
                {
                    "q": [
                        -0.3218955192255296,
                        0.39223581085029047,
                        -0.824033263992018,
                        0.09906061474022271,
                        1.2146318142947183,
                        0.79069286231245
                    ],
                    "t": 187.0
                },
                {
                    "q": [
                        1.4381994965024492,
                        -0.5174988667368066,
                        -1.3573402424316683,
                        0.2441849474550369,
                        1.3585513994894454,
                        0.9164381701896847
                    ],
                    "t": 257.97932126282876
                }
            ]
        },
        {
            "name": "a1_",
            "type": 0,
            "start_conf": [
                1.4381994965024507,
                -0.5174988667368083,
                -1.3573402424316672,
                0.24418494745503594,
                1.3585513994894443,
                0.9164381701896838
            ],
            "goal_conf": [
                -1.7583814667340496,
                -0.1618302595182965,
                -1.8717267287223343,
                0.17394267730844537,
                1.5428978999573386,
                2.2235365219110563
            ],
            "start_time": 258,
            "success": 1,
            "planning_time": 1297,
            "path": [
                {
                    "q": [
                        1.4381994965024507,
                        -0.5174988667368083,
                        -1.3573402424316672,
                        0.24418494745503594,
                        1.3585513994894443,
                        0.9164381701896838
                    ],
                    "t": 258.0
                },
                {
                    "q": [
                        1.678482657389702,
                        -0.48181605116985826,
                        -1.223438018642437,
                        0.1444439924149845,
                        1.521108220362751,
                        -0.02520292683550851
                    ],
                    "t": 268.0
                },
                {
                    "q": [
                        0.46150020467988606,
                        -0.35557135851753574,
                        -0.44825921095100607,
                        -0.1757655666973142,
                        0.517886213603153,
                        -0.9776798287052204
                    ],
                    "t": 288.29322228447325
                },
                {
                    "q": [
                        -1.7583814667340496,
                        -0.1618302595182965,
                        -1.8717267287223343,
                        0.17394267730844537,
                        1.5428978999573386,
                        2.2235365219110563
                    ],
                    "t": 331.2231994872216
                }
            ]
        },
        {
            "name": "a1_",
            "type": 0,
            "start_conf": [
                -1.7583814667340496,
                -0.16183025951829677,
                -1.871726728722333,
                0.17394267730844426,
                1.5428978999573388,
                2.2235365219110577
            ],
            "goal_conf": [
                0.0,
                0.5,
                -1.2,
                0.0,
                1.57,
                1.57
            ],
            "start_time": 332,
            "success": 1,
            "planning_time": 107,
            "path": [
                {
                    "q": [
                        -1.7583814667340496,
                        -0.16183025951829677,
                        -1.871726728722333,
                        0.17394267730844426,
                        1.5428978999573388,
                        2.2235365219110577
                    ],
                    "t": 332.0
                },
                {
                    "q": [
                        -1.1843832292908907,
                        0.13944338541060808,
                        -2.1747507575875873,
                        -0.07433014491003972,
                        0.9141155817850476,
                        2.04766709786237
                    ],
                    "t": 342.0
                },
                {
                    "q": [
                        0.0,
                        0.5,
                        -1.2,
                        0.0,
                        1.57,
                        1.57
                    ],
                    "t": 359.7491727367202
                }
            ]
        }
    ]
}