{
    "objects": [
        {
            "goal_pos": [
                0.32857804967166837,
                -0.930489088721302,
                0.07500000000000001
            ],
            "goal_quat": [
                0.9926583602835709,
                -0.0,
                -0.0,
                -0.12095197294435689
            ],
            "shape": [
                0.03,
                0.3,
                0.05
            ],
            "start_pos": [
                0.3803281864530384,
                0.28445436462646345,
                0.15100000000000002
            ],
            "start_quat": [
                0.057704349805657994,
                0.0,
                0.0,
                0.9983337157551608
            ]
        },
        {
            "goal_pos": [
                0.932494514541443,
                -0.6752425906922784,
                0.07500000000000001
            ],
            "goal_quat": [
                0.9957988947633818,
                -0.0,
                -0.0,
                -0.091567249538398
            ],
            "shape": [
                0.03,
                0.3,
                0.05
            ],
            "start_pos": [
                -0.3922729796512165,
                0.3257818314199433,
                0.551
            ],
            "start_quat": [
                0.9628641337133222,
                -0.0,
                -0.0,
                -0.26998640708097427
            ]
        },
        {
            "goal_pos": [
                -0.8547779957396333,
                -0.7505566520619613,
                0.07500000000000001
            ],
            "goal_quat": [
                0.39152531444002164,
                0.0,
                0.0,
                0.920167337038564
            ],
            "shape": [
                0.03,
                0.3,
                0.05
            ],
            "start_pos": [
                0.010960606270141969,
                0.29154210740425,
                0.15100000000000002
            ],
            "start_quat": [
                0.3033785798055072,
                -0.0,
                -0.0,
                -0.9528701051639691
            ]
        }
    ]
}