{
    "objects": [
        {
            "goal_pos": [
                0.4875494221789041,
                -0.9364756937533751,
                0.07500000000000001
            ],
            "goal_quat": [
                0.827274238184934,
                -0.0,
                -0.0,
                -0.5617983044078516
            ],
            "shape": [
                0.03,
                0.3,
                0.05
            ],
            "start_pos": [
                0.40397903403480107,
                0.3208583414318766,
                0.15100000000000002
            ],
            "start_quat": [
                0.38532608288285214,
                -0.0,
                -0.0,
                -0.9227804776056748
            ]
        },
        {
            "goal_pos": [
                1.0830446141095882,
                -0.3835043697173218,
                0.07500000000000001
            ],
            "goal_quat": [
                0.8251751997476928,
                0.0,
                0.0,
                0.5648768801441206
            ],
            "shape": [
                0.03,
                0.3,
                0.05
            ],
            "start_pos": [
                -0.41503111170319423,
                0.28072897759166127,
                0.551
            ],
            "start_quat": [
                0.9992303151492126,
                -0.0,
                -0.0,
                -0.039227251838553925
            ]
        },
        {
            "goal_pos": [
                -0.3164871749572065,
                -0.8364930072631278,
                0.07500000000000001
            ],
            "goal_quat": [
                0.0007110626672677624,
                0.0,
                0.0,
                0.9999997471949097
            ],
            "shape": [
                0.03,
                0.3,
                0.05
            ],
            "start_pos": [
                0.0006575738499029794,
                0.31873395487972495,
                0.15100000000000002
            ],
            "start_quat": [
                0.93383517533001,
                -0.0,
                -0.0,
                -0.3577035998090729
            ]
        }
    ]
}