{
    "objects": [
        {
            "goal_pos": [
                -0.9418812964985424,
                -0.5722039743640315,
                0.07500000000000001
            ],
            "goal_quat": [
                0.3908466141642407,
                -0.0,
                -0.0,
                -0.9204558241416854
            ],
            "shape": [
                0.03,
                0.3,
                0.05
            ],
            "start_pos": [
                0.3949230101701969,
                0.2915293427528635,
                0.15100000000000002
            ],
            "start_quat": [
                0.6007834996923644,
                -0.0,
                -0.0,
                -0.7994117753056899
            ]
        },
        {
            "goal_pos": [
                -0.7698716099505151,
                -0.8267011936189179,
                0.07500000000000001
            ],
            "goal_quat": [
                0.8872249186838671,
                -0.0,
                -0.0,
                -0.4613371258270955
            ],
            "shape": [
                0.03,
                0.3,
                0.05
            ],
            "start_pos": [
                -0.41365600645343015,
                0.3432812577444819,
                0.551
            ],
            "start_quat": [
                0.9297312719510223,
                -0.0,
                -0.0,
                -0.36823872957136666
            ]
        }
    ]
}