{
    "objects": [
        {
            "goal_pos": [
                0.5400918346717825,
                -0.4732357415554761,
                0.22500000000000003
            ],
            "goal_quat": [
                0.9273629064548421,
                -0.0,
                -0.0,
                -0.37416311914942646
            ],
            "shape": [
                0.36,
                0.19,
                0.35000000000000003
            ],
            "start_pos": [
                -0.6177414571792806,
                -0.5380900752630322,
                0.22500000000000003
            ],
            "start_quat": [
                0.6977938294879543,
                -0.0,
                -0.0,
                -0.7162986608451365
            ]
        },
        {
            "goal_pos": [
                0.015261575149133594,
                -0.6388101511848021,
                0.22000000000000003
            ],
            "goal_quat": [
                0.2426711535606356,
                -0.0,
                -0.0,
                -0.9701086079555992
            ],
            "shape": [
                0.09,
                0.08,
                0.34
            ],
            "start_pos": [
                -0.3616538427859861,
                -0.4036488539703792,
                0.22000000000000003
            ],
            "start_quat": [
                0.252074823438752,
                -0.0,
                -0.0,
                -0.9677077468886575
            ]
        },
        {
            "goal_pos": [
                0.09741468558025815,
                -0.44964395100761945,
                0.2
            ],
            "goal_quat": [
                0.7984983133670979,
                -0.0,
                -0.0,
                -0.6019970461305436
            ],
            "shape": [
                0.13,
                0.1,
                0.3
            ],
            "start_pos": [
                -0.28296672757138647,
                -0.254505509626649,
                0.2
            ],
            "start_quat": [
                0.9629672035810763,
                0.0,
                0.0,
                0.26961855430819626
            ]
        },
        {
            "goal_pos": [
                -0.1730671092021915,
                -0.523447058403278,
                0.085
            ],
            "goal_quat": [
                0.999180090703696,
                -0.0,
                -0.0,
                -0.0404863722918457
            ],
            "shape": [
                0.14,
                0.15,
                0.07
            ],
            "start_pos": [
                0.007141964351642993,
                -0.288607910129,
                0.085
            ],
            "start_quat": [
                0.6641170797899107,
                0.0,
                0.0,
                0.7476285871549598
            ]
        }
    ]
}