{
    "robots": [
        {
            "base_pos": [
                -0.08020465059140747,
                -0.5502847475061302,
                0.0
            ],
            "base_quat": [
                1.0,
                0.0,
                0.0,
                0.0
            ],
            "home_pose": [
                0.0,
                0.5,
                -1.2,
                0.0,
                1.57,
                1.57
            ],
            "start_pose": [
                0.0,
                0.5,
                -1.2,
                0.0,
                1.57,
                1.57
            ],
            "type": "ur5_vacuum"
        },
        {
            "base_pos": [
                0.4994960881268009,
                0.18415720955346604,
                0.0
            ],
            "base_quat": [
                6.123233995736766e-17,
                0.0,
                0.0,
                1.0
            ],
            "home_pose": [
                0.0,
                0.5,
                -1.2,
                0.0,
                1.57,
                1.57
            ],
            "start_pose": [
                0.0,
                0.5,
                -1.2,
                0.0,
                1.57,
                1.57
            ],
            "type": "ur5_vacuum"
        },
        {
            "base_pos": [
                -0.41929143753539344,
                0.3661275379526643,
                0.0
            ],
            "base_quat": [
                1.0,
                0.0,
                0.0,
                0.0
            ],
            "home_pose": [
                0.0,
                0.5,
                -1.2,
                0.0,
                1.57,
                1.57
            ],
            "start_pose": [
                0.0,
                0.5,
                -1.2,
                0.0,
                1.57,
                1.57
            ],
            "type": "ur5_vacuum"
        }
    ]
}