{
    "objects": [
        {
            "goal_pos": [
                -0.6787840190732749,
                -0.7180080122342196,
                0.19
            ],
            "goal_quat": [
                0.7838220319196793,
                0.0,
                0.0,
                0.6209855250143157
            ],
            "shape": [
                0.31,
                0.07,
                0.28
            ],
            "start_pos": [
                0.9311288574498063,
                0.1927841344832304,
                0.19
            ],
            "start_quat": [
                0.3424626560566769,
                0.0,
                0.0,
                0.9395314413081695
            ]
        }
    ]
}