{
    "objects": [
        {
            "goal_pos": [
                -0.15757084692426837,
                0.6419534753025952,
                0.20500000000000002
            ],
            "goal_quat": [
                0.9583686249931441,
                0.0,
                0.0,
                0.2855338484816648
            ],
            "shape": [
                0.2,
                0.2,
                0.31
            ],
            "start_pos": [
                0.9279918977593345,
                0.583955478820275,
                0.20500000000000002
            ],
            "start_quat": [
                0.8584288956789003,
                0.0,
                0.0,
                0.5129325794522158
            ]
        },
        {
            "goal_pos": [
                -0.938733166901585,
                -0.3070340158881692,
                0.16999999999999998
            ],
            "goal_quat": [
                0.31445851999501195,
                0.0,
                0.0,
                0.9492712147761285
            ],
            "shape": [
                0.14,
                0.22,
                0.24
            ],
            "start_pos": [
                0.6364910519220324,
                0.7626961130259269,
                0.16999999999999998
            ],
            "start_quat": [
                0.06700658498290425,
                0.0,
                0.0,
                0.9977525332310256
            ]
        },
        {
            "goal_pos": [
                -0.35074507835676566,
                0.2602905896904124,
                0.12000000000000001
            ],
            "goal_quat": [
                0.3346367546673648,
                -0.0,
                -0.0,
                -0.9423471984495385
            ],
            "shape": [
                0.18,
                0.24,
                0.14
            ],
            "start_pos": [
                -0.5735542596797651,
                -0.8030486449677936,
                0.12000000000000001
            ],
            "start_quat": [
                0.6537416249138154,
                -0.0,
                -0.0,
                -0.7567178389961772
            ]
        }
    ]
}