{
    "objects": [
        {
            "goal_pos": [
                -0.8502991160914569,
                1.2620339170521517,
                0.21000000000000002
            ],
            "goal_quat": [
                0.7792680208110933,
                -0.0,
                -0.0,
                -0.626690794364463
            ],
            "shape": [
                0.28,
                0.25,
                0.32
            ],
            "start_pos": [
                0.8928247085623267,
                -1.1411599047334877,
                0.21000000000000002
            ],
            "start_quat": [
                0.5607749150551062,
                -0.0,
                -0.0,
                -0.8279682932606407
            ]
        },
        {
            "goal_pos": [
                0.9785179288588113,
                -0.21901589331534121,
                0.155
            ],
            "goal_quat": [
                0.5324083031878682,
                0.0,
                0.0,
                0.8464876837241136
            ],
            "shape": [
                0.21,
                0.23,
                0.21
            ],
            "start_pos": [
                1.2029633691029584,
                0.5906938077418092,
                0.155
            ],
            "start_quat": [
                0.9999641793158303,
                -0.0,
                -0.0,
                -0.00846404662192686
            ]
        }
    ]
}