{
    "objects": [
        {
            "goal_pos": [
                0.6342697045086543,
                -0.554794792456371,
                0.21500000000000002
            ],
            "goal_quat": [
                0.8284574344345033,
                0.0,
                0.0,
                0.5600520326989277
            ],
            "shape": [
                0.33,
                0.24,
                0.33
            ],
            "start_pos": [
                -0.2421317973606794,
                -0.3467042512303572,
                0.21500000000000002
            ],
            "start_quat": [
                0.9305459165186981,
                0.0,
                0.0,
                0.36617522752143705
            ]
        },
        {
            "goal_pos": [
                0.2753981831772619,
                -0.38844996634516227,
                0.085
            ],
            "goal_quat": [
                0.5496901463198066,
                0.0,
                0.0,
                0.8353686270377345
            ],
            "shape": [
                0.18,
                0.32,
                0.07
            ],
            "start_pos": [
                -0.6073153958972044,
                -0.584766739160055,
                0.085
            ],
            "start_quat": [
                0.7088483795142417,
                -0.0,
                -0.0,
                -0.7053608827118452
            ]
        }
    ]
}