{
    "objects": [
        {
            "goal_pos": [
                0.894413506765392,
                0.7598584912433017,
                0.115
            ],
            "goal_quat": [
                0.7576218701304029,
                0.0,
                0.0,
                0.6526937274864152
            ],
            "shape": [
                0.11,
                0.07,
                0.13
            ],
            "start_pos": [
                0.1725559422583295,
                -0.572484031519835,
                0.115
            ],
            "start_quat": [
                0.9706763018127912,
                -0.0,
                -0.0,
                -0.24039034319007713
            ]
        }
    ]
}