{
    "objects": [
        {
            "goal_pos": [
                0.8822831871472797,
                -0.6328583604690532,
                0.07500000000000001
            ],
            "goal_quat": [
                0.879173154647917,
                0.0,
                0.0,
                0.47650242826918493
            ],
            "shape": [
                0.03,
                0.3,
                0.05
            ],
            "start_pos": [
                0.3838919280376552,
                0.262597030074247,
                0.15100000000000002
            ],
            "start_quat": [
                0.7907442106708591,
                -0.0,
                -0.0,
                -0.6121467089599683
            ]
        },
        {
            "goal_pos": [
                -0.9832026414658409,
                -0.47361782994597484,
                0.07500000000000001
            ],
            "goal_quat": [
                0.28946544021431314,
                0.0,
                0.0,
                0.957188465727379
            ],
            "shape": [
                0.03,
                0.3,
                0.05
            ],
            "start_pos": [
                -0.39911339850279703,
                0.288298078682355,
                0.551
            ],
            "start_quat": [
                0.7962153954622978,
                -0.0,
                -0.0,
                -0.6050132593826492
            ]
        }
    ]
}