{
    "objects": [
        {
            "goal_pos": [
                1.0557670353922195,
                -0.5215462248234377,
                0.07500000000000001
            ],
            "goal_quat": [
                0.6599562810901731,
                -0.0,
                -0.0,
                -0.7513040044147431
            ],
            "shape": [
                0.03,
                0.3,
                0.05
            ],
            "start_pos": [
                0.39289338406604735,
                0.31415111816587277,
                0.15100000000000002
            ],
            "start_quat": [
                0.27009009061543165,
                -0.0,
                -0.0,
                -0.9628350549036673
            ]
        },
        {
            "goal_pos": [
                0.015346852157307134,
                -0.8345432203024774,
                0.07500000000000001
            ],
            "goal_quat": [
                0.9894900696157135,
                -0.0,
                -0.0,
                -0.1446008372447767
            ],
            "shape": [
                0.03,
                0.3,
                0.05
            ],
            "start_pos": [
                -0.38959014218555216,
                0.27821229512213125,
                0.551
            ],
            "start_quat": [
                0.9732455507372124,
                0.0,
                0.0,
                0.22976748675611186
            ]
        },
        {
            "goal_pos": [
                -0.9314107658633181,
                -0.3860888600015775,
                0.07500000000000001
            ],
            "goal_quat": [
                0.9938356689238432,
                0.0,
                0.0,
                0.11086326341352727
            ],
            "shape": [
                0.03,
                0.3,
                0.05
            ],
            "start_pos": [
                0.0012086133299800753,
                0.33320517748923506,
                0.15100000000000002
            ],
            "start_quat": [
                0.5165812687513407,
                0.0,
                0.0,
                0.8562381635825719
            ]
        },
        {
            "goal_pos": [
                0.569047698139571,
                -0.8024551959506112,
                0.07500000000000001
            ],
            "goal_quat": [
                0.4183196822975085,
                -0.0,
                -0.0,
                -0.9082998642532716
            ],
            "shape": [
                0.03,
                0.3,
                0.05
            ],
            "start_pos": [
                0.0014234700692553025,
                0.30996985381223385,
                0.551
            ],
            "start_quat": [
                0.9624782940561593,
                0.0,
                0.0,
                0.2713586804779706
            ]
        }
    ]
}