{
    "robots": [
        {
            "base_pos": [
                -0.7456447020208894,
                -0.6139056933524991,
                0.0
            ],
            "base_quat": [
                1.0,
                0.0,
                0.0,
                0.0
            ],
            "home_pose": [
                0.0,
                0.5,
                -1.2,
                0.0,
                1.57,
                1.57
            ],
            "start_pose": [
                0.0,
                0.5,
                -1.2,
                0.0,
                1.57,
                1.57
            ],
            "type": "ur5_vacuum"
        },
        {
            "base_pos": [
                0.7554990071716218,
                0.6699246073055181,
                0.0
            ],
            "base_quat": [
                6.123233995736766e-17,
                0.0,
                0.0,
                1.0
            ],
            "home_pose": [
                0.0,
                0.5,
                -1.2,
                0.0,
                1.57,
                1.57
            ],
            "start_pose": [
                0.0,
                0.5,
                -1.2,
                0.0,
                1.57,
                1.57
            ],
            "type": "ur5_vacuum"
        },
        {
            "base_pos": [
                0.5491066423182919,
                -0.6128955368650517,
                0.0
            ],
            "base_quat": [
                6.123233995736766e-17,
                0.0,
                0.0,
                1.0
            ],
            "home_pose": [
                0.0,
                0.5,
                -1.2,
                0.0,
                1.57,
                1.57
            ],
            "start_pose": [
                0.0,
                0.5,
                -1.2,
                0.0,
                1.57,
                1.57
            ],
            "type": "ur5_vacuum"
        },
        {
            "base_pos": [
                -0.5589609474690241,
                0.5568766229120328,
                0.0
            ],
            "base_quat": [
                1.0,
                0.0,
                0.0,
                0.0
            ],
            "home_pose": [
                0.0,
                0.5,
                -1.2,
                0.0,
                1.57,
                1.57
            ],
            "start_pose": [
                0.0,
                0.5,
                -1.2,
                0.0,
                1.57,
                1.57
            ],
            "type": "ur5_vacuum"
        }
    ]
}