{
    "objects": [
        {
            "goal_pos": [
                0.7780224497789587,
                -0.7119760549007288,
                0.07500000000000001
            ],
            "goal_quat": [
                0.6047057122581833,
                -0.0,
                -0.0,
                -0.7964489949534265
            ],
            "shape": [
                0.03,
                0.3,
                0.05
            ],
            "start_pos": [
                0.41373913831108955,
                0.25671490015496473,
                0.15100000000000002
            ],
            "start_quat": [
                0.8189240969004791,
                0.0,
                0.0,
                0.5739018413594217
            ]
        },
        {
            "goal_pos": [
                0.4100001452430281,
                -0.850310698838737,
                0.07500000000000001
            ],
            "goal_quat": [
                0.9678241950725776,
                -0.0,
                -0.0,
                -0.2516273582743286
            ],
            "shape": [
                0.03,
                0.3,
                0.05
            ],
            "start_pos": [
                -0.4019340861976324,
                0.26256992362593845,
                0.551
            ],
            "start_quat": [
                0.9614285388371608,
                -0.0,
                -0.0,
                -0.2750548394583193
            ]
        },
        {
            "goal_pos": [
                -0.06385039029451223,
                -0.8313501529338572,
                0.07500000000000001
            ],
            "goal_quat": [
                0.7878280871154574,
                -0.0,
                -0.0,
                -0.6158952063070464
            ],
            "shape": [
                0.03,
                0.3,
                0.05
            ],
            "start_pos": [
                0.01939442819818235,
                0.2542061712715125,
                0.15100000000000002
            ],
            "start_quat": [
                0.2742354927765569,
                0.0,
                0.0,
                0.9616625679008198
            ]
        },
        {
            "goal_pos": [
                1.0041375286070784,
                -0.3853349056482188,
                0.07500000000000001
            ],
            "goal_quat": [
                0.3638753525670218,
                -0.0,
                -0.0,
                -0.9314476516660641
            ],
            "shape": [
                0.03,
                0.3,
                0.05
            ],
            "start_pos": [
                0.010305133243050532,
                0.2767923157043753,
                0.551
            ],
            "start_quat": [
                0.7322013586920277,
                0.0,
                0.0,
                0.6810882250704006
            ]
        }
    ]
}